README.md
setup.py
src/dwimgs/__init__.py
src/dwimgs/run.py
src/dwimgs.egg-info/PKG-INFO
src/dwimgs.egg-info/SOURCES.txt
src/dwimgs.egg-info/dependency_links.txt
src/dwimgs.egg-info/entry_points.txt
src/dwimgs.egg-info/requires.txt
src/dwimgs.egg-info/top_level.txt
src/dwimgs/batch_dw/__init__.py
src/dwimgs/batch_dw/terminal_downloader.py
src/dwimgs/utils/__init__.py
src/dwimgs/utils/ansi_escape_codes.py
src/dwimgs/utils/image_downloader.py
src/dwimgs/utils/package_info.py