Metadata-Version: 2.1
Name: dwimgs
Version: 1.0.2
Summary: Command line utility to bulk download images from a text file
Home-page: https://github.com/amsaid1989/bulk-download-images
Author: Abdelrahman Said
Author-email: said.abdelrahman89@gmail.com
License: MIT
Platform: OS Independent
